{
  "$schema": "http://json-schema.org/draft-07/schema",
  "type": "object",
  "additionalProperties": false,
  "required": ["id", "account_id", "name", "active_from", "active_to", "created_at", "updated_at"],
  "properties": {
    "id": {"type": "integer"},
    "account_id": {"type": "integer"},
    "name": {"type": "string"},
    "width": {"type": "integer"},
    "height": {"type": "integer"},
    "active_from": {"type": "string"},
    "active_to": {"type": "string"},
    "created_at": {"type": "string"},
    "updated_at": {"type": "string"}
  }
}